cryptnumpy/__init__.py
cryptnumpy/encrypt_decrypt.py
cryptnumpy/tests/__init__.py
cryptnumpy/tests/test_IO.py
cryptnumpy-0.1.dist-info/LICENSE.txt
cryptnumpy-0.1.dist-info/METADATA
cryptnumpy-0.1.dist-info/WHEEL
cryptnumpy-0.1.dist-info/top_level.txt
cryptnumpy-0.1.dist-info/RECORD
