Metadata-Version: 2.2
Name: CryptNumPy
Version: 0.1
Summary: A tool for encryption and decryption of numpy arrays and pandas dataframes. Port of `cryptpandas`.
Home-page: https://github.com/lungoruscello/cryptnumpy
Author: S. Langenbach
License: MIT
Classifier: Programming Language :: Python :: 3
Classifier: License :: OSI Approved :: MIT License
Classifier: Operating System :: OS Independent
Requires-Python: >=3.6
License-File: LICENSE.txt
Requires-Dist: pandas
Requires-Dist: numpy
Requires-Dist: cryptography>=41.0.4
Requires-Dist: pyarrow>=14.0.1
Provides-Extra: dev
Requires-Dist: pytest>=7.0; extra == "dev"
Requires-Dist: twine>=4.0.2; extra == "dev"
Dynamic: author
Dynamic: classifier
Dynamic: description
Dynamic: description-content-type
Dynamic: home-page
Dynamic: license
Dynamic: provides-extra
Dynamic: requires-dist
Dynamic: requires-python
Dynamic: summary
